evomatic/__init__.py
evomatic/_version.py
evomatic/annealing.py
evomatic/competition.py
evomatic/evolve.py
evomatic/fitness.py
evomatic/mutation.py
evomatic/plots.py
evomatic/py.typed
evomatic/recombination.py
evomatic-0.0.6.dist-info/LICENSE
evomatic-0.0.6.dist-info/METADATA
evomatic-0.0.6.dist-info/WHEEL
evomatic-0.0.6.dist-info/top_level.txt
evomatic-0.0.6.dist-info/RECORD
