Metadata-Version: 2.1
Name: evomatic
Version: 0.0.6
Summary: Evolutionary algorithm for development of alloy materials
Home-page: https://github.com/Robert-Forrest/evomatic
Author: Robert Forrest
Author-email: robertforrest@live.com
License: BSD 3-Clause License
Platform: unix
Platform: linux
Platform: osx
Platform: cygwin
Platform: win32
Classifier: Programming Language :: Python :: 3
Classifier: Programming Language :: Python :: 3 :: Only
Classifier: License :: OSI Approved :: BSD License
Classifier: Operating System :: OS Independent
Requires-Python: >=3.6
License-File: LICENSE
Requires-Dist: pandas
Requires-Dist: numpy
Requires-Dist: matplotlib
Requires-Dist: metallurgy (>=0.0.16)
Requires-Dist: elementy
Requires-Dist: cerebral
Requires-Dist: omegaconf
Requires-Dist: bokeh (==2.4.3)
Requires-Dist: selenium
Provides-Extra: dev
Requires-Dist: pre-commit ; extra == 'dev'
Requires-Dist: tox (==3.24.3) ; extra == 'dev'
Requires-Dist: pytest (==6.2.5) ; extra == 'dev'
Requires-Dist: pytest-cov (==2.12.1) ; extra == 'dev'
